[
  {
    "run_id": 1626,
    "timestamp": "2025-05-23T03:08:27.771055",
    "stage": "checkout",
    "status": "INFO",
    "message": "Starting checkout",
    "host": "Rama",
    "user": "Ramazan",
    "pid": 14456,
    "thread": 16576,
    "label": 0
  },
  {
    "run_id": 1626,
    "timestamp": "2025-05-23T03:08:34.067339",
    "stage": "checkout",
    "status": "INFO",
    "message": "Checking out branch",
    "host": "Rama",
    "user": "Ramazan",
    "pid": 14456,
    "thread": 16576,
    "label": 0
  },
  {
    "run_id": 1626,
    "timestamp": "2025-05-23T03:08:44.567209",
    "stage": "checkout",
    "status": "INFO",
    "message": "Repository checked out successfully",
    "host": "Rama",
    "user": "Ramazan",
    "pid": 14456,
    "thread": 16576,
    "duration_sec": 10.49987,
    "label": 0
  },
  {
    "run_id": 1626,
    "timestamp": "2025-05-23T03:08:47.459421",
    "stage": "install",
    "status": "INFO",
    "message": "Starting install",
    "host": "Rama",
    "user": "Ramazan",
    "pid": 14456,
    "thread": 16576,
    "label": 0
  },
  {
    "run_id": 1626,
    "timestamp": "2025-05-23T03:08:58.870041",
    "stage": "install",
    "status": "INFO",
    "message": "Downloading packages",
    "host": "Rama",
    "user": "Ramazan",
    "pid": 14456,
    "thread": 16576,
    "label": 0
  },
  {
    "run_id": 1626,
    "timestamp": "2025-05-23T03:09:08.183839",
    "stage": "install",
    "status": "INFO",
    "message": "Resolving dependencies",
    "host": "Rama",
    "user": "Ramazan",
    "pid": 14456,
    "thread": 16576,
    "label": 0
  },
  {
    "run_id": 1626,
    "timestamp": "2025-05-23T03:09:24.966992",
    "stage": "install",
    "status": "INFO",
    "message": "All packages installed",
    "host": "Rama",
    "user": "Ramazan",
    "pid": 14456,
    "thread": 16576,
    "duration_sec": 16.783153,
    "label": 0
  },
  {
    "run_id": 1626,
    "timestamp": "2025-05-23T03:09:26.185074",
    "stage": "build",
    "status": "INFO",
    "message": "Starting build",
    "host": "Rama",
    "user": "Ramazan",
    "pid": 14456,
    "thread": 16576,
    "label": 0
  },
  {
    "run_id": 1626,
    "timestamp": "2025-05-23T03:09:48.718161",
    "stage": "build",
    "status": "INFO",
    "message": "Build completed in 22.53s",
    "host": "Rama",
    "user": "Ramazan",
    "pid": 14456,
    "thread": 16576,
    "duration_sec": 22.533087,
    "label": 0
  },
  {
    "run_id": 1626,
    "timestamp": "2025-05-23T03:09:49.855739",
    "stage": "test",
    "status": "INFO",
    "message": "Starting test",
    "host": "Rama",
    "user": "Ramazan",
    "pid": 14456,
    "thread": 16576,
    "label": 0
  },
  {
    "run_id": 1626,
    "timestamp": "2025-05-23T03:10:00.892649",
    "stage": "test",
    "status": "INFO",
    "message": "Executing integration suite",
    "host": "Rama",
    "user": "Ramazan",
    "pid": 14456,
    "thread": 16576,
    "label": 0
  },
  {
    "run_id": 1626,
    "timestamp": "2025-05-23T03:10:08.419676",
    "stage": "test",
    "status": "INFO",
    "message": "Running unit tests",
    "host": "Rama",
    "user": "Ramazan",
    "pid": 14456,
    "thread": 16576,
    "label": 0
  },
  {
    "run_id": 1626,
    "timestamp": "2025-05-23T03:10:32.966194",
    "stage": "test",
    "status": "INFO",
    "message": "All tests passed",
    "host": "Rama",
    "user": "Ramazan",
    "pid": 14456,
    "thread": 16576,
    "duration_sec": 24.546518,
    "label": 0
  },
  {
    "run_id": 1626,
    "timestamp": "2025-05-23T03:10:34.651762",
    "stage": "deploy",
    "status": "INFO",
    "message": "Starting deploy",
    "host": "Rama",
    "user": "Ramazan",
    "pid": 14456,
    "thread": 16576,
    "label": 0
  },
  {
    "run_id": 1626,
    "timestamp": "2025-05-23T03:11:03.126655",
    "stage": "deploy",
    "status": "INFO",
    "message": "Deployment succeeded",
    "host": "Rama",
    "user": "Ramazan",
    "pid": 14456,
    "thread": 16576,
    "duration_sec": 28.474893,
    "label": 0
  }
]