[
  {
    "run_id": 4983,
    "timestamp": "2025-06-09T15:02:57.153252",
    "stage": "checkout",
    "status": "INFO",
    "message": "Starting checkout",
    "host": "Rama",
    "user": "Ramazan",
    "pid": 14456,
    "thread": 16576,
    "label": 0
  },
  {
    "run_id": 4983,
    "timestamp": "2025-06-09T15:03:09.489056",
    "stage": "checkout",
    "status": "INFO",
    "message": "Repository checked out successfully",
    "host": "Rama",
    "user": "Ramazan",
    "pid": 14456,
    "thread": 16576,
    "duration_sec": 12.335804,
    "label": 0
  },
  {
    "run_id": 4983,
    "timestamp": "2025-06-09T15:03:12.331873",
    "stage": "install",
    "status": "INFO",
    "message": "Starting install",
    "host": "Rama",
    "user": "Ramazan",
    "pid": 14456,
    "thread": 16576,
    "label": 0
  },
  {
    "run_id": 4983,
    "timestamp": "2025-06-09T15:03:21.414737",
    "stage": "install",
    "status": "INFO",
    "message": "Verifying checksums",
    "host": "Rama",
    "user": "Ramazan",
    "pid": 14456,
    "thread": 16576,
    "label": 0
  },
  {
    "run_id": 4983,
    "timestamp": "2025-06-09T15:03:26.331075",
    "stage": "install",
    "status": "INFO",
    "message": "Verifying checksums",
    "host": "Rama",
    "user": "Ramazan",
    "pid": 14456,
    "thread": 16576,
    "label": 0
  },
  {
    "run_id": 4983,
    "timestamp": "2025-06-09T15:03:51.419449",
    "stage": "install",
    "status": "INFO",
    "message": "All packages installed",
    "host": "Rama",
    "user": "Ramazan",
    "pid": 14456,
    "thread": 16576,
    "duration_sec": 25.088374,
    "label": 0
  },
  {
    "run_id": 4983,
    "timestamp": "2025-06-09T15:03:53.087808",
    "stage": "build",
    "status": "INFO",
    "message": "Starting build",
    "host": "Rama",
    "user": "Ramazan",
    "pid": 14456,
    "thread": 16576,
    "label": 0
  },
  {
    "run_id": 4983,
    "timestamp": "2025-06-09T15:03:55.161116",
    "stage": "build",
    "status": "INFO",
    "message": "Starting compiler",
    "host": "Rama",
    "user": "Ramazan",
    "pid": 14456,
    "thread": 16576,
    "label": 0
  },
  {
    "run_id": 4983,
    "timestamp": "2025-06-09T15:04:19.409258",
    "stage": "build",
    "status": "INFO",
    "message": "Build completed in 24.25s",
    "host": "Rama",
    "user": "Ramazan",
    "pid": 14456,
    "thread": 16576,
    "duration_sec": 24.248142,
    "label": 0
  },
  {
    "run_id": 4983,
    "timestamp": "2025-06-09T15:04:20.781608",
    "stage": "test",
    "status": "INFO",
    "message": "Starting test",
    "host": "Rama",
    "user": "Ramazan",
    "pid": 14456,
    "thread": 16576,
    "label": 0
  },
  {
    "run_id": 4983,
    "timestamp": "2025-06-09T15:04:31.521627",
    "stage": "test",
    "status": "INFO",
    "message": "Running unit tests",
    "host": "Rama",
    "user": "Ramazan",
    "pid": 14456,
    "thread": 16576,
    "label": 0
  },
  {
    "run_id": 4983,
    "timestamp": "2025-06-09T15:04:40.078634",
    "stage": "test",
    "status": "INFO",
    "message": "All tests passed",
    "host": "Rama",
    "user": "Ramazan",
    "pid": 14456,
    "thread": 16576,
    "duration_sec": 8.557007,
    "label": 0
  },
  {
    "run_id": 4983,
    "timestamp": "2025-06-09T15:04:42.954868",
    "stage": "deploy",
    "status": "INFO",
    "message": "Starting deploy",
    "host": "Rama",
    "user": "Ramazan",
    "pid": 14456,
    "thread": 16576,
    "label": 0
  },
  {
    "run_id": 4983,
    "timestamp": "2025-06-09T15:04:46.548515",
    "stage": "deploy",
    "status": "INFO",
    "message": "Uploading artifacts",
    "host": "Rama",
    "user": "Ramazan",
    "pid": 14456,
    "thread": 16576,
    "label": 0
  },
  {
    "run_id": 4983,
    "timestamp": "2025-06-09T15:04:47.949445",
    "stage": "deploy",
    "status": "INFO",
    "message": "Uploading artifacts",
    "host": "Rama",
    "user": "Ramazan",
    "pid": 14456,
    "thread": 16576,
    "label": 0
  },
  {
    "run_id": 4983,
    "timestamp": "2025-06-09T15:04:58.236123",
    "stage": "deploy",
    "status": "INFO",
    "message": "Deployment succeeded",
    "host": "Rama",
    "user": "Ramazan",
    "pid": 14456,
    "thread": 16576,
    "duration_sec": 10.286678,
    "label": 0
  }
]