[
  {
    "run_id": 9236,
    "timestamp": "2025-07-01T19:49:25.622176",
    "stage": "checkout",
    "status": "INFO",
    "message": "Starting checkout",
    "host": "Rama",
    "user": "Ramazan",
    "pid": 14456,
    "thread": 16576,
    "label": 0
  },
  {
    "run_id": 9236,
    "timestamp": "2025-07-01T19:49:33.758571",
    "stage": "checkout",
    "status": "INFO",
    "message": "Fetching remote refs",
    "host": "Rama",
    "user": "Ramazan",
    "pid": 14456,
    "thread": 16576,
    "label": 0
  },
  {
    "run_id": 9236,
    "timestamp": "2025-07-01T19:49:35.946834",
    "stage": "checkout",
    "status": "INFO",
    "message": "Checking out branch",
    "host": "Rama",
    "user": "Ramazan",
    "pid": 14456,
    "thread": 16576,
    "label": 0
  },
  {
    "run_id": 9236,
    "timestamp": "2025-07-01T19:49:47.250900",
    "stage": "checkout",
    "status": "INFO",
    "message": "Repository checked out successfully",
    "host": "Rama",
    "user": "Ramazan",
    "pid": 14456,
    "thread": 16576,
    "duration_sec": 11.304066,
    "label": 0
  },
  {
    "run_id": 9236,
    "timestamp": "2025-07-01T19:49:49.437624",
    "stage": "install",
    "status": "INFO",
    "message": "Starting install",
    "host": "Rama",
    "user": "Ramazan",
    "pid": 14456,
    "thread": 16576,
    "label": 0
  },
  {
    "run_id": 9236,
    "timestamp": "2025-07-01T19:50:01.792458",
    "stage": "install",
    "status": "INFO",
    "message": "Verifying checksums",
    "host": "Rama",
    "user": "Ramazan",
    "pid": 14456,
    "thread": 16576,
    "label": 0
  },
  {
    "run_id": 9236,
    "timestamp": "2025-07-01T19:50:22.974958",
    "stage": "install",
    "status": "INFO",
    "message": "All packages installed",
    "host": "Rama",
    "user": "Ramazan",
    "pid": 14456,
    "thread": 16576,
    "duration_sec": 21.1825,
    "label": 0
  },
  {
    "run_id": 9236,
    "timestamp": "2025-07-01T19:50:25.317132",
    "stage": "build",
    "status": "INFO",
    "message": "Starting build",
    "host": "Rama",
    "user": "Ramazan",
    "pid": 14456,
    "thread": 16576,
    "label": 0
  },
  {
    "run_id": 9236,
    "timestamp": "2025-07-01T19:50:30.869858",
    "stage": "build",
    "status": "INFO",
    "message": "Linking binaries",
    "host": "Rama",
    "user": "Ramazan",
    "pid": 14456,
    "thread": 16576,
    "label": 0
  },
  {
    "run_id": 9236,
    "timestamp": "2025-07-01T19:50:40.377123",
    "stage": "build",
    "status": "INFO",
    "message": "Compiling modules",
    "host": "Rama",
    "user": "Ramazan",
    "pid": 14456,
    "thread": 16576,
    "label": 0
  },
  {
    "run_id": 9236,
    "timestamp": "2025-07-01T19:50:54.912929",
    "stage": "build",
    "status": "INFO",
    "message": "Build completed in 14.54s",
    "host": "Rama",
    "user": "Ramazan",
    "pid": 14456,
    "thread": 16576,
    "duration_sec": 14.535806,
    "label": 0
  },
  {
    "run_id": 9236,
    "timestamp": "2025-07-01T19:50:57.333041",
    "stage": "test",
    "status": "INFO",
    "message": "Starting test",
    "host": "Rama",
    "user": "Ramazan",
    "pid": 14456,
    "thread": 16576,
    "label": 0
  },
  {
    "run_id": 9236,
    "timestamp": "2025-07-01T19:51:25.290919",
    "stage": "test",
    "status": "INFO",
    "message": "All tests passed",
    "host": "Rama",
    "user": "Ramazan",
    "pid": 14456,
    "thread": 16576,
    "duration_sec": 27.957878,
    "label": 0
  },
  {
    "run_id": 9236,
    "timestamp": "2025-07-01T19:51:26.312981",
    "stage": "deploy",
    "status": "INFO",
    "message": "Starting deploy",
    "host": "Rama",
    "user": "Ramazan",
    "pid": 14456,
    "thread": 16576,
    "label": 0
  },
  {
    "run_id": 9236,
    "timestamp": "2025-07-01T19:51:51.818318",
    "stage": "deploy",
    "status": "INFO",
    "message": "Deployment succeeded",
    "host": "Rama",
    "user": "Ramazan",
    "pid": 14456,
    "thread": 16576,
    "duration_sec": 25.505337,
    "label": 0
  }
]