[
  {
    "run_id": 9356,
    "timestamp": "2025-07-02T10:49:03.553966",
    "stage": "checkout",
    "status": "INFO",
    "message": "Starting checkout",
    "host": "Rama",
    "user": "Ramazan",
    "pid": 14456,
    "thread": 16576,
    "label": 0
  },
  {
    "run_id": 9356,
    "timestamp": "2025-07-02T10:49:31.918868",
    "stage": "checkout",
    "status": "INFO",
    "message": "Repository checked out successfully",
    "host": "Rama",
    "user": "Ramazan",
    "pid": 14456,
    "thread": 16576,
    "duration_sec": 28.364902,
    "label": 0
  },
  {
    "run_id": 9356,
    "timestamp": "2025-07-02T10:49:33.360351",
    "stage": "install",
    "status": "INFO",
    "message": "Starting install",
    "host": "Rama",
    "user": "Ramazan",
    "pid": 14456,
    "thread": 16576,
    "label": 0
  },
  {
    "run_id": 9356,
    "timestamp": "2025-07-02T10:49:38.818505",
    "stage": "install",
    "status": "INFO",
    "message": "Downloading packages",
    "host": "Rama",
    "user": "Ramazan",
    "pid": 14456,
    "thread": 16576,
    "label": 0
  },
  {
    "run_id": 9356,
    "timestamp": "2025-07-02T10:49:41.340065",
    "stage": "install",
    "status": "INFO",
    "message": "Resolving dependencies",
    "host": "Rama",
    "user": "Ramazan",
    "pid": 14456,
    "thread": 16576,
    "label": 0
  },
  {
    "run_id": 9356,
    "timestamp": "2025-07-02T10:49:48.229638",
    "stage": "install",
    "status": "INFO",
    "message": "All packages installed",
    "host": "Rama",
    "user": "Ramazan",
    "pid": 14456,
    "thread": 16576,
    "duration_sec": 6.889573,
    "label": 0
  },
  {
    "run_id": 9356,
    "timestamp": "2025-07-02T10:49:49.458893",
    "stage": "build",
    "status": "INFO",
    "message": "Starting build",
    "host": "Rama",
    "user": "Ramazan",
    "pid": 14456,
    "thread": 16576,
    "label": 0
  },
  {
    "run_id": 9356,
    "timestamp": "2025-07-02T10:50:01.308284",
    "stage": "build",
    "status": "INFO",
    "message": "Compiling modules",
    "host": "Rama",
    "user": "Ramazan",
    "pid": 14456,
    "thread": 16576,
    "label": 0
  },
  {
    "run_id": 9356,
    "timestamp": "2025-07-02T10:50:25.893763",
    "stage": "build",
    "status": "INFO",
    "message": "Build completed in 24.59s",
    "host": "Rama",
    "user": "Ramazan",
    "pid": 14456,
    "thread": 16576,
    "duration_sec": 24.585479,
    "label": 0
  },
  {
    "run_id": 9356,
    "timestamp": "2025-07-02T10:50:27.628242",
    "stage": "test",
    "status": "INFO",
    "message": "Starting test",
    "host": "Rama",
    "user": "Ramazan",
    "pid": 14456,
    "thread": 16576,
    "label": 0
  },
  {
    "run_id": 9356,
    "timestamp": "2025-07-02T10:50:35.548025",
    "stage": "test",
    "status": "INFO",
    "message": "Collecting test results",
    "host": "Rama",
    "user": "Ramazan",
    "pid": 14456,
    "thread": 16576,
    "label": 0
  },
  {
    "run_id": 9356,
    "timestamp": "2025-07-02T10:50:37.379010",
    "stage": "test",
    "status": "INFO",
    "message": "Running unit tests",
    "host": "Rama",
    "user": "Ramazan",
    "pid": 14456,
    "thread": 16576,
    "label": 0
  },
  {
    "run_id": 9356,
    "timestamp": "2025-07-02T10:50:49.822883",
    "stage": "test",
    "status": "ERROR",
    "message": "Test suite failed: 1 test did not pass",
    "host": "Rama",
    "user": "Ramazan",
    "pid": 14456,
    "thread": 16576,
    "duration_sec": 12.443873,
    "label": 1
  },
  {
    "run_id": 9356,
    "timestamp": "2025-07-02T10:50:52.319740",
    "stage": "deploy",
    "status": "INFO",
    "message": "Starting deploy",
    "host": "Rama",
    "user": "Ramazan",
    "pid": 14456,
    "thread": 16576,
    "label": 0
  },
  {
    "run_id": 9356,
    "timestamp": "2025-07-02T10:51:00.749481",
    "stage": "deploy",
    "status": "INFO",
    "message": "Uploading artifacts",
    "host": "Rama",
    "user": "Ramazan",
    "pid": 14456,
    "thread": 16576,
    "label": 0
  },
  {
    "run_id": 9356,
    "timestamp": "2025-07-02T10:51:05.532094",
    "stage": "deploy",
    "status": "INFO",
    "message": "Verifying health checks",
    "host": "Rama",
    "user": "Ramazan",
    "pid": 14456,
    "thread": 16576,
    "label": 0
  },
  {
    "run_id": 9356,
    "timestamp": "2025-07-02T10:51:18.604561",
    "stage": "deploy",
    "status": "INFO",
    "message": "Deployment succeeded",
    "host": "Rama",
    "user": "Ramazan",
    "pid": 14456,
    "thread": 16576,
    "duration_sec": 13.072467,
    "label": 0
  }
]