[
  {
    "run_id": 1074,
    "timestamp": "2025-05-20T06:00:17.307908",
    "stage": "checkout",
    "status": "INFO",
    "message": "Starting checkout",
    "host": "Rama",
    "user": "Ramazan",
    "pid": 14456,
    "thread": 16576,
    "label": 0
  },
  {
    "run_id": 1074,
    "timestamp": "2025-05-20T06:00:40.868915",
    "stage": "checkout",
    "status": "INFO",
    "message": "Repository checked out successfully",
    "host": "Rama",
    "user": "Ramazan",
    "pid": 14456,
    "thread": 16576,
    "duration_sec": 23.561007,
    "label": 0
  },
  {
    "run_id": 1074,
    "timestamp": "2025-05-20T06:00:43.090294",
    "stage": "install",
    "status": "INFO",
    "message": "Starting install",
    "host": "Rama",
    "user": "Ramazan",
    "pid": 14456,
    "thread": 16576,
    "label": 0
  },
  {
    "run_id": 1074,
    "timestamp": "2025-05-20T06:01:04.770439",
    "stage": "install",
    "status": "INFO",
    "message": "All packages installed",
    "host": "Rama",
    "user": "Ramazan",
    "pid": 14456,
    "thread": 16576,
    "duration_sec": 21.680145,
    "label": 0
  },
  {
    "run_id": 1074,
    "timestamp": "2025-05-20T06:01:06.834922",
    "stage": "build",
    "status": "INFO",
    "message": "Starting build",
    "host": "Rama",
    "user": "Ramazan",
    "pid": 14456,
    "thread": 16576,
    "label": 0
  },
  {
    "run_id": 1074,
    "timestamp": "2025-05-20T06:01:19.781625",
    "stage": "build",
    "status": "INFO",
    "message": "Compiling modules",
    "host": "Rama",
    "user": "Ramazan",
    "pid": 14456,
    "thread": 16576,
    "label": 0
  },
  {
    "run_id": 1074,
    "timestamp": "2025-05-20T06:01:42.013370",
    "stage": "build",
    "status": "INFO",
    "message": "Build completed in 22.23s",
    "host": "Rama",
    "user": "Ramazan",
    "pid": 14456,
    "thread": 16576,
    "duration_sec": 22.231745,
    "label": 0
  },
  {
    "run_id": 1074,
    "timestamp": "2025-05-20T06:01:43.592291",
    "stage": "test",
    "status": "INFO",
    "message": "Starting test",
    "host": "Rama",
    "user": "Ramazan",
    "pid": 14456,
    "thread": 16576,
    "label": 0
  },
  {
    "run_id": 1074,
    "timestamp": "2025-05-20T06:01:54.550296",
    "stage": "test",
    "status": "ERROR",
    "message": "Test suite failed: 1 test did not pass",
    "host": "Rama",
    "user": "Ramazan",
    "pid": 14456,
    "thread": 16576,
    "duration_sec": 10.958005,
    "label": 1
  },
  {
    "run_id": 1074,
    "timestamp": "2025-05-20T06:01:56.314528",
    "stage": "deploy",
    "status": "INFO",
    "message": "Starting deploy",
    "host": "Rama",
    "user": "Ramazan",
    "pid": 14456,
    "thread": 16576,
    "label": 0
  },
  {
    "run_id": 1074,
    "timestamp": "2025-05-20T06:02:08.607335",
    "stage": "deploy",
    "status": "INFO",
    "message": "Uploading artifacts",
    "host": "Rama",
    "user": "Ramazan",
    "pid": 14456,
    "thread": 16576,
    "label": 0
  },
  {
    "run_id": 1074,
    "timestamp": "2025-05-20T06:02:11.088662",
    "stage": "deploy",
    "status": "INFO",
    "message": "Uploading artifacts",
    "host": "Rama",
    "user": "Ramazan",
    "pid": 14456,
    "thread": 16576,
    "label": 0
  },
  {
    "run_id": 1074,
    "timestamp": "2025-05-20T06:02:33.588154",
    "stage": "deploy",
    "status": "INFO",
    "message": "Deployment succeeded",
    "host": "Rama",
    "user": "Ramazan",
    "pid": 14456,
    "thread": 16576,
    "duration_sec": 22.499492,
    "label": 0
  }
]