[
  {
    "run_id": 3117,
    "timestamp": "2025-05-30T22:08:34.804271",
    "stage": "checkout",
    "status": "INFO",
    "message": "Starting checkout",
    "host": "Rama",
    "user": "Ramazan",
    "pid": 14456,
    "thread": 16576,
    "label": 0
  },
  {
    "run_id": 3117,
    "timestamp": "2025-05-30T22:08:53.483497",
    "stage": "checkout",
    "status": "INFO",
    "message": "Repository checked out successfully",
    "host": "Rama",
    "user": "Ramazan",
    "pid": 14456,
    "thread": 16576,
    "duration_sec": 18.679226,
    "label": 0
  },
  {
    "run_id": 3117,
    "timestamp": "2025-05-30T22:08:55.694650",
    "stage": "install",
    "status": "INFO",
    "message": "Starting install",
    "host": "Rama",
    "user": "Ramazan",
    "pid": 14456,
    "thread": 16576,
    "label": 0
  },
  {
    "run_id": 3117,
    "timestamp": "2025-05-30T22:09:08.854305",
    "stage": "install",
    "status": "INFO",
    "message": "Resolving dependencies",
    "host": "Rama",
    "user": "Ramazan",
    "pid": 14456,
    "thread": 16576,
    "label": 0
  },
  {
    "run_id": 3117,
    "timestamp": "2025-05-30T22:09:11.777566",
    "stage": "install",
    "status": "INFO",
    "message": "Resolving dependencies",
    "host": "Rama",
    "user": "Ramazan",
    "pid": 14456,
    "thread": 16576,
    "label": 0
  },
  {
    "run_id": 3117,
    "timestamp": "2025-05-30T22:09:27.044063",
    "stage": "install",
    "status": "INFO",
    "message": "All packages installed",
    "host": "Rama",
    "user": "Ramazan",
    "pid": 14456,
    "thread": 16576,
    "duration_sec": 15.266497,
    "label": 0
  },
  {
    "run_id": 3117,
    "timestamp": "2025-05-30T22:09:29.652177",
    "stage": "build",
    "status": "INFO",
    "message": "Starting build",
    "host": "Rama",
    "user": "Ramazan",
    "pid": 14456,
    "thread": 16576,
    "label": 0
  },
  {
    "run_id": 3117,
    "timestamp": "2025-05-30T22:09:54.557287",
    "stage": "build",
    "status": "INFO",
    "message": "Build completed in 24.91s",
    "host": "Rama",
    "user": "Ramazan",
    "pid": 14456,
    "thread": 16576,
    "duration_sec": 24.90511,
    "label": 0
  },
  {
    "run_id": 3117,
    "timestamp": "2025-05-30T22:09:55.841143",
    "stage": "test",
    "status": "INFO",
    "message": "Starting test",
    "host": "Rama",
    "user": "Ramazan",
    "pid": 14456,
    "thread": 16576,
    "label": 0
  },
  {
    "run_id": 3117,
    "timestamp": "2025-05-30T22:10:06.645854",
    "stage": "test",
    "status": "INFO",
    "message": "Collecting test results",
    "host": "Rama",
    "user": "Ramazan",
    "pid": 14456,
    "thread": 16576,
    "label": 0
  },
  {
    "run_id": 3117,
    "timestamp": "2025-05-30T22:10:16.427321",
    "stage": "test",
    "status": "INFO",
    "message": "Running unit tests",
    "host": "Rama",
    "user": "Ramazan",
    "pid": 14456,
    "thread": 16576,
    "label": 0
  },
  {
    "run_id": 3117,
    "timestamp": "2025-05-30T22:10:28.838279",
    "stage": "test",
    "status": "INFO",
    "message": "All tests passed",
    "host": "Rama",
    "user": "Ramazan",
    "pid": 14456,
    "thread": 16576,
    "duration_sec": 12.410958,
    "label": 0
  },
  {
    "run_id": 3117,
    "timestamp": "2025-05-30T22:10:31.726549",
    "stage": "deploy",
    "status": "INFO",
    "message": "Starting deploy",
    "host": "Rama",
    "user": "Ramazan",
    "pid": 14456,
    "thread": 16576,
    "label": 0
  },
  {
    "run_id": 3117,
    "timestamp": "2025-05-30T22:10:42.792062",
    "stage": "deploy",
    "status": "INFO",
    "message": "Deployment succeeded",
    "host": "Rama",
    "user": "Ramazan",
    "pid": 14456,
    "thread": 16576,
    "duration_sec": 11.065513,
    "label": 0
  }
]