[
  {
    "run_id": 4319,
    "timestamp": "2025-06-06T03:54:39.295774",
    "stage": "checkout",
    "status": "INFO",
    "message": "Starting checkout",
    "host": "Rama",
    "user": "Ramazan",
    "pid": 14456,
    "thread": 16576,
    "label": 0
  },
  {
    "run_id": 4319,
    "timestamp": "2025-06-06T03:54:44.275142",
    "stage": "checkout",
    "status": "INFO",
    "message": "Checking out branch",
    "host": "Rama",
    "user": "Ramazan",
    "pid": 14456,
    "thread": 16576,
    "label": 0
  },
  {
    "run_id": 4319,
    "timestamp": "2025-06-06T03:55:08.848884",
    "stage": "checkout",
    "status": "INFO",
    "message": "Repository checked out successfully",
    "host": "Rama",
    "user": "Ramazan",
    "pid": 14456,
    "thread": 16576,
    "duration_sec": 24.573742,
    "label": 0
  },
  {
    "run_id": 4319,
    "timestamp": "2025-06-06T03:55:09.896161",
    "stage": "install",
    "status": "INFO",
    "message": "Starting install",
    "host": "Rama",
    "user": "Ramazan",
    "pid": 14456,
    "thread": 16576,
    "label": 0
  },
  {
    "run_id": 4319,
    "timestamp": "2025-06-06T03:55:15.090211",
    "stage": "install",
    "status": "INFO",
    "message": "Downloading packages",
    "host": "Rama",
    "user": "Ramazan",
    "pid": 14456,
    "thread": 16576,
    "label": 0
  },
  {
    "run_id": 4319,
    "timestamp": "2025-06-06T03:55:18.399787",
    "stage": "install",
    "status": "INFO",
    "message": "Verifying checksums",
    "host": "Rama",
    "user": "Ramazan",
    "pid": 14456,
    "thread": 16576,
    "label": 0
  },
  {
    "run_id": 4319,
    "timestamp": "2025-06-06T03:55:44.029169",
    "stage": "install",
    "status": "INFO",
    "message": "All packages installed",
    "host": "Rama",
    "user": "Ramazan",
    "pid": 14456,
    "thread": 16576,
    "duration_sec": 25.629382,
    "label": 0
  },
  {
    "run_id": 4319,
    "timestamp": "2025-06-06T03:55:46.842394",
    "stage": "build",
    "status": "INFO",
    "message": "Starting build",
    "host": "Rama",
    "user": "Ramazan",
    "pid": 14456,
    "thread": 16576,
    "label": 0
  },
  {
    "run_id": 4319,
    "timestamp": "2025-06-06T03:56:15.110092",
    "stage": "build",
    "status": "INFO",
    "message": "Build completed in 28.27s",
    "host": "Rama",
    "user": "Ramazan",
    "pid": 14456,
    "thread": 16576,
    "duration_sec": 28.267698,
    "label": 0
  },
  {
    "run_id": 4319,
    "timestamp": "2025-06-06T03:56:17.233108",
    "stage": "test",
    "status": "INFO",
    "message": "Starting test",
    "host": "Rama",
    "user": "Ramazan",
    "pid": 14456,
    "thread": 16576,
    "label": 0
  },
  {
    "run_id": 4319,
    "timestamp": "2025-06-06T03:56:20.646280",
    "stage": "test",
    "status": "INFO",
    "message": "Running unit tests",
    "host": "Rama",
    "user": "Ramazan",
    "pid": 14456,
    "thread": 16576,
    "label": 0
  },
  {
    "run_id": 4319,
    "timestamp": "2025-06-06T03:56:47.499724",
    "stage": "test",
    "status": "INFO",
    "message": "All tests passed",
    "host": "Rama",
    "user": "Ramazan",
    "pid": 14456,
    "thread": 16576,
    "duration_sec": 26.853444,
    "label": 0
  },
  {
    "run_id": 4319,
    "timestamp": "2025-06-06T03:56:50.490729",
    "stage": "deploy",
    "status": "INFO",
    "message": "Starting deploy",
    "host": "Rama",
    "user": "Ramazan",
    "pid": 14456,
    "thread": 16576,
    "label": 0
  },
  {
    "run_id": 4319,
    "timestamp": "2025-06-06T03:56:55.347131",
    "stage": "deploy",
    "status": "INFO",
    "message": "Uploading artifacts",
    "host": "Rama",
    "user": "Ramazan",
    "pid": 14456,
    "thread": 16576,
    "label": 0
  },
  {
    "run_id": 4319,
    "timestamp": "2025-06-06T03:57:15.295468",
    "stage": "deploy",
    "status": "INFO",
    "message": "Deployment succeeded",
    "host": "Rama",
    "user": "Ramazan",
    "pid": 14456,
    "thread": 16576,
    "duration_sec": 19.948337,
    "label": 0
  }
]