[
  {
    "run_id": 6276,
    "timestamp": "2025-06-16T10:36:02.808177",
    "stage": "checkout",
    "status": "INFO",
    "message": "Starting checkout",
    "host": "Rama",
    "user": "Ramazan",
    "pid": 14456,
    "thread": 16576,
    "label": 0
  },
  {
    "run_id": 6276,
    "timestamp": "2025-06-16T10:36:13.124719",
    "stage": "checkout",
    "status": "INFO",
    "message": "Validating commit object",
    "host": "Rama",
    "user": "Ramazan",
    "pid": 14456,
    "thread": 16576,
    "label": 0
  },
  {
    "run_id": 6276,
    "timestamp": "2025-06-16T10:36:15.948080",
    "stage": "checkout",
    "status": "INFO",
    "message": "Fetching remote refs",
    "host": "Rama",
    "user": "Ramazan",
    "pid": 14456,
    "thread": 16576,
    "label": 0
  },
  {
    "run_id": 6276,
    "timestamp": "2025-06-16T10:36:45.933761",
    "stage": "checkout",
    "status": "INFO",
    "message": "Repository checked out successfully",
    "host": "Rama",
    "user": "Ramazan",
    "pid": 14456,
    "thread": 16576,
    "duration_sec": 29.985681,
    "label": 0
  },
  {
    "run_id": 6276,
    "timestamp": "2025-06-16T10:36:48.534249",
    "stage": "install",
    "status": "INFO",
    "message": "Starting install",
    "host": "Rama",
    "user": "Ramazan",
    "pid": 14456,
    "thread": 16576,
    "label": 0
  },
  {
    "run_id": 6276,
    "timestamp": "2025-06-16T10:36:56.183197",
    "stage": "install",
    "status": "INFO",
    "message": "Downloading packages",
    "host": "Rama",
    "user": "Ramazan",
    "pid": 14456,
    "thread": 16576,
    "label": 0
  },
  {
    "run_id": 6276,
    "timestamp": "2025-06-16T10:37:04.310223",
    "stage": "install",
    "status": "INFO",
    "message": "Resolving dependencies",
    "host": "Rama",
    "user": "Ramazan",
    "pid": 14456,
    "thread": 16576,
    "label": 0
  },
  {
    "run_id": 6276,
    "timestamp": "2025-06-16T10:37:21.025905",
    "stage": "install",
    "status": "INFO",
    "message": "All packages installed",
    "host": "Rama",
    "user": "Ramazan",
    "pid": 14456,
    "thread": 16576,
    "duration_sec": 16.715682,
    "label": 0
  },
  {
    "run_id": 6276,
    "timestamp": "2025-06-16T10:37:23.400119",
    "stage": "build",
    "status": "INFO",
    "message": "Starting build",
    "host": "Rama",
    "user": "Ramazan",
    "pid": 14456,
    "thread": 16576,
    "label": 0
  },
  {
    "run_id": 6276,
    "timestamp": "2025-06-16T10:37:29.712951",
    "stage": "build",
    "status": "INFO",
    "message": "Starting compiler",
    "host": "Rama",
    "user": "Ramazan",
    "pid": 14456,
    "thread": 16576,
    "label": 0
  },
  {
    "run_id": 6276,
    "timestamp": "2025-06-16T10:37:33.304109",
    "stage": "build",
    "status": "INFO",
    "message": "Starting compiler",
    "host": "Rama",
    "user": "Ramazan",
    "pid": 14456,
    "thread": 16576,
    "label": 0
  },
  {
    "run_id": 6276,
    "timestamp": "2025-06-16T10:37:59.951883",
    "stage": "build",
    "status": "INFO",
    "message": "Build completed in 26.65s",
    "host": "Rama",
    "user": "Ramazan",
    "pid": 14456,
    "thread": 16576,
    "duration_sec": 26.647774,
    "label": 0
  },
  {
    "run_id": 6276,
    "timestamp": "2025-06-16T10:38:01.843877",
    "stage": "test",
    "status": "INFO",
    "message": "Starting test",
    "host": "Rama",
    "user": "Ramazan",
    "pid": 14456,
    "thread": 16576,
    "label": 0
  },
  {
    "run_id": 6276,
    "timestamp": "2025-06-16T10:38:10.264342",
    "stage": "test",
    "status": "INFO",
    "message": "Running unit tests",
    "host": "Rama",
    "user": "Ramazan",
    "pid": 14456,
    "thread": 16576,
    "label": 0
  },
  {
    "run_id": 6276,
    "timestamp": "2025-06-16T10:38:24.566977",
    "stage": "test",
    "status": "INFO",
    "message": "All tests passed",
    "host": "Rama",
    "user": "Ramazan",
    "pid": 14456,
    "thread": 16576,
    "duration_sec": 14.302635,
    "label": 0
  },
  {
    "run_id": 6276,
    "timestamp": "2025-06-16T10:38:27.520119",
    "stage": "deploy",
    "status": "INFO",
    "message": "Starting deploy",
    "host": "Rama",
    "user": "Ramazan",
    "pid": 14456,
    "thread": 16576,
    "label": 0
  },
  {
    "run_id": 6276,
    "timestamp": "2025-06-16T10:38:40.066995",
    "stage": "deploy",
    "status": "INFO",
    "message": "Uploading artifacts",
    "host": "Rama",
    "user": "Ramazan",
    "pid": 14456,
    "thread": 16576,
    "label": 0
  },
  {
    "run_id": 6276,
    "timestamp": "2025-06-16T10:39:02.866033",
    "stage": "deploy",
    "status": "INFO",
    "message": "Deployment succeeded",
    "host": "Rama",
    "user": "Ramazan",
    "pid": 14456,
    "thread": 16576,
    "duration_sec": 22.799038,
    "label": 0
  }
]