[
  {
    "run_id": 1399,
    "timestamp": "2025-05-21T23:30:56.976033",
    "stage": "checkout",
    "status": "INFO",
    "message": "Starting checkout",
    "host": "Rama",
    "user": "Ramazan",
    "pid": 14456,
    "thread": 16576,
    "label": 0
  },
  {
    "run_id": 1399,
    "timestamp": "2025-05-21T23:31:29.194379",
    "stage": "checkout",
    "status": "INFO",
    "message": "Repository checked out successfully",
    "host": "Rama",
    "user": "Ramazan",
    "pid": 14456,
    "thread": 16576,
    "duration_sec": 32.218346,
    "label": 0
  },
  {
    "run_id": 1399,
    "timestamp": "2025-05-21T23:31:30.411412",
    "stage": "install",
    "status": "INFO",
    "message": "Starting install",
    "host": "Rama",
    "user": "Ramazan",
    "pid": 14456,
    "thread": 16576,
    "label": 0
  },
  {
    "run_id": 1399,
    "timestamp": "2025-05-21T23:31:45.072730",
    "stage": "install",
    "status": "INFO",
    "message": "Verifying checksums",
    "host": "Rama",
    "user": "Ramazan",
    "pid": 14456,
    "thread": 16576,
    "label": 0
  },
  {
    "run_id": 1399,
    "timestamp": "2025-05-21T23:31:55.031549",
    "stage": "install",
    "status": "INFO",
    "message": "Verifying checksums",
    "host": "Rama",
    "user": "Ramazan",
    "pid": 14456,
    "thread": 16576,
    "label": 0
  },
  {
    "run_id": 1399,
    "timestamp": "2025-05-21T23:32:09.956497",
    "stage": "install",
    "status": "INFO",
    "message": "All packages installed",
    "host": "Rama",
    "user": "Ramazan",
    "pid": 14456,
    "thread": 16576,
    "duration_sec": 14.924948,
    "label": 0
  },
  {
    "run_id": 1399,
    "timestamp": "2025-05-21T23:32:12.098580",
    "stage": "build",
    "status": "INFO",
    "message": "Starting build",
    "host": "Rama",
    "user": "Ramazan",
    "pid": 14456,
    "thread": 16576,
    "label": 0
  },
  {
    "run_id": 1399,
    "timestamp": "2025-05-21T23:32:25.931421",
    "stage": "build",
    "status": "INFO",
    "message": "Build completed in 13.83s",
    "host": "Rama",
    "user": "Ramazan",
    "pid": 14456,
    "thread": 16576,
    "duration_sec": 13.832841,
    "label": 0
  },
  {
    "run_id": 1399,
    "timestamp": "2025-05-21T23:32:28.460946",
    "stage": "test",
    "status": "INFO",
    "message": "Starting test",
    "host": "Rama",
    "user": "Ramazan",
    "pid": 14456,
    "thread": 16576,
    "label": 0
  },
  {
    "run_id": 1399,
    "timestamp": "2025-05-21T23:32:59.366984",
    "stage": "test",
    "status": "INFO",
    "message": "All tests passed",
    "host": "Rama",
    "user": "Ramazan",
    "pid": 14456,
    "thread": 16576,
    "duration_sec": 30.906038,
    "label": 0
  },
  {
    "run_id": 1399,
    "timestamp": "2025-05-21T23:33:01.449480",
    "stage": "deploy",
    "status": "INFO",
    "message": "Starting deploy",
    "host": "Rama",
    "user": "Ramazan",
    "pid": 14456,
    "thread": 16576,
    "label": 0
  },
  {
    "run_id": 1399,
    "timestamp": "2025-05-21T23:33:13.766980",
    "stage": "deploy",
    "status": "INFO",
    "message": "Deployment succeeded",
    "host": "Rama",
    "user": "Ramazan",
    "pid": 14456,
    "thread": 16576,
    "duration_sec": 12.3175,
    "label": 0
  }
]