[
  {
    "run_id": 2665,
    "timestamp": "2025-05-28T13:19:37.162937",
    "stage": "checkout",
    "status": "INFO",
    "message": "Starting checkout",
    "host": "Rama",
    "user": "Ramazan",
    "pid": 14456,
    "thread": 16576,
    "label": 0
  },
  {
    "run_id": 2665,
    "timestamp": "2025-05-28T13:19:50.511046",
    "stage": "checkout",
    "status": "INFO",
    "message": "Repository checked out successfully",
    "host": "Rama",
    "user": "Ramazan",
    "pid": 14456,
    "thread": 16576,
    "duration_sec": 13.348109,
    "label": 0
  },
  {
    "run_id": 2665,
    "timestamp": "2025-05-28T13:19:53.317213",
    "stage": "install",
    "status": "INFO",
    "message": "Starting install",
    "host": "Rama",
    "user": "Ramazan",
    "pid": 14456,
    "thread": 16576,
    "label": 0
  },
  {
    "run_id": 2665,
    "timestamp": "2025-05-28T13:20:24.221095",
    "stage": "install",
    "status": "INFO",
    "message": "All packages installed",
    "host": "Rama",
    "user": "Ramazan",
    "pid": 14456,
    "thread": 16576,
    "duration_sec": 30.903882,
    "label": 0
  },
  {
    "run_id": 2665,
    "timestamp": "2025-05-28T13:20:26.680734",
    "stage": "build",
    "status": "INFO",
    "message": "Starting build",
    "host": "Rama",
    "user": "Ramazan",
    "pid": 14456,
    "thread": 16576,
    "label": 0
  },
  {
    "run_id": 2665,
    "timestamp": "2025-05-28T13:20:49.677420",
    "stage": "build",
    "status": "INFO",
    "message": "Build completed in 23.00s",
    "host": "Rama",
    "user": "Ramazan",
    "pid": 14456,
    "thread": 16576,
    "duration_sec": 22.996686,
    "label": 0
  },
  {
    "run_id": 2665,
    "timestamp": "2025-05-28T13:20:51.640732",
    "stage": "test",
    "status": "INFO",
    "message": "Starting test",
    "host": "Rama",
    "user": "Ramazan",
    "pid": 14456,
    "thread": 16576,
    "label": 0
  },
  {
    "run_id": 2665,
    "timestamp": "2025-05-28T13:20:59.296004",
    "stage": "test",
    "status": "INFO",
    "message": "Collecting test results",
    "host": "Rama",
    "user": "Ramazan",
    "pid": 14456,
    "thread": 16576,
    "label": 0
  },
  {
    "run_id": 2665,
    "timestamp": "2025-05-28T13:21:03.874277",
    "stage": "test",
    "status": "INFO",
    "message": "Running unit tests",
    "host": "Rama",
    "user": "Ramazan",
    "pid": 14456,
    "thread": 16576,
    "label": 0
  },
  {
    "run_id": 2665,
    "timestamp": "2025-05-28T13:21:16.958560",
    "stage": "test",
    "status": "INFO",
    "message": "All tests passed",
    "host": "Rama",
    "user": "Ramazan",
    "pid": 14456,
    "thread": 16576,
    "duration_sec": 13.084283,
    "label": 0
  },
  {
    "run_id": 2665,
    "timestamp": "2025-05-28T13:21:19.952273",
    "stage": "deploy",
    "status": "INFO",
    "message": "Starting deploy",
    "host": "Rama",
    "user": "Ramazan",
    "pid": 14456,
    "thread": 16576,
    "label": 0
  },
  {
    "run_id": 2665,
    "timestamp": "2025-05-28T13:21:28.940546",
    "stage": "deploy",
    "status": "INFO",
    "message": "Restarting services",
    "host": "Rama",
    "user": "Ramazan",
    "pid": 14456,
    "thread": 16576,
    "label": 0
  },
  {
    "run_id": 2665,
    "timestamp": "2025-05-28T13:21:30.647252",
    "stage": "deploy",
    "status": "INFO",
    "message": "Uploading artifacts",
    "host": "Rama",
    "user": "Ramazan",
    "pid": 14456,
    "thread": 16576,
    "label": 0
  },
  {
    "run_id": 2665,
    "timestamp": "2025-05-28T13:21:44.141236",
    "stage": "deploy",
    "status": "INFO",
    "message": "Deployment succeeded",
    "host": "Rama",
    "user": "Ramazan",
    "pid": 14456,
    "thread": 16576,
    "duration_sec": 13.493984,
    "label": 0
  }
]