[
  {
    "run_id": 470,
    "timestamp": "2025-05-17T02:37:54.243994",
    "stage": "checkout",
    "status": "INFO",
    "message": "Starting checkout",
    "host": "Rama",
    "user": "Ramazan",
    "pid": 14456,
    "thread": 16576,
    "label": 0
  },
  {
    "run_id": 470,
    "timestamp": "2025-05-17T02:38:06.194968",
    "stage": "checkout",
    "status": "INFO",
    "message": "Checking out branch",
    "host": "Rama",
    "user": "Ramazan",
    "pid": 14456,
    "thread": 16576,
    "label": 0
  },
  {
    "run_id": 470,
    "timestamp": "2025-05-17T02:38:13.413956",
    "stage": "checkout",
    "status": "INFO",
    "message": "Validating commit object",
    "host": "Rama",
    "user": "Ramazan",
    "pid": 14456,
    "thread": 16576,
    "label": 0
  },
  {
    "run_id": 470,
    "timestamp": "2025-05-17T02:38:24.255465",
    "stage": "checkout",
    "status": "INFO",
    "message": "Repository checked out successfully",
    "host": "Rama",
    "user": "Ramazan",
    "pid": 14456,
    "thread": 16576,
    "duration_sec": 10.841509,
    "label": 0
  },
  {
    "run_id": 470,
    "timestamp": "2025-05-17T02:38:26.016207",
    "stage": "install",
    "status": "INFO",
    "message": "Starting install",
    "host": "Rama",
    "user": "Ramazan",
    "pid": 14456,
    "thread": 16576,
    "label": 0
  },
  {
    "run_id": 470,
    "timestamp": "2025-05-17T02:38:52.744025",
    "stage": "install",
    "status": "INFO",
    "message": "All packages installed",
    "host": "Rama",
    "user": "Ramazan",
    "pid": 14456,
    "thread": 16576,
    "duration_sec": 26.727818,
    "label": 0
  },
  {
    "run_id": 470,
    "timestamp": "2025-05-17T02:38:54.040158",
    "stage": "build",
    "status": "INFO",
    "message": "Starting build",
    "host": "Rama",
    "user": "Ramazan",
    "pid": 14456,
    "thread": 16576,
    "label": 0
  },
  {
    "run_id": 470,
    "timestamp": "2025-05-17T02:39:03.003350",
    "stage": "build",
    "status": "INFO",
    "message": "Linking binaries",
    "host": "Rama",
    "user": "Ramazan",
    "pid": 14456,
    "thread": 16576,
    "label": 0
  },
  {
    "run_id": 470,
    "timestamp": "2025-05-17T02:39:28.814056",
    "stage": "build",
    "status": "INFO",
    "message": "Build completed in 25.81s",
    "host": "Rama",
    "user": "Ramazan",
    "pid": 14456,
    "thread": 16576,
    "duration_sec": 25.810706,
    "label": 0
  },
  {
    "run_id": 470,
    "timestamp": "2025-05-17T02:39:30.924070",
    "stage": "test",
    "status": "INFO",
    "message": "Starting test",
    "host": "Rama",
    "user": "Ramazan",
    "pid": 14456,
    "thread": 16576,
    "label": 0
  },
  {
    "run_id": 470,
    "timestamp": "2025-05-17T02:39:41.432387",
    "stage": "test",
    "status": "INFO",
    "message": "All tests passed",
    "host": "Rama",
    "user": "Ramazan",
    "pid": 14456,
    "thread": 16576,
    "duration_sec": 10.508317,
    "label": 0
  },
  {
    "run_id": 470,
    "timestamp": "2025-05-17T02:39:44.229459",
    "stage": "deploy",
    "status": "INFO",
    "message": "Starting deploy",
    "host": "Rama",
    "user": "Ramazan",
    "pid": 14456,
    "thread": 16576,
    "label": 0
  },
  {
    "run_id": 470,
    "timestamp": "2025-05-17T02:40:13.332815",
    "stage": "deploy",
    "status": "INFO",
    "message": "Deployment succeeded",
    "host": "Rama",
    "user": "Ramazan",
    "pid": 14456,
    "thread": 16576,
    "duration_sec": 29.103356,
    "label": 0
  }
]