[
  {
    "run_id": 1465,
    "timestamp": "2025-05-22T07:31:52.029172",
    "stage": "checkout",
    "status": "INFO",
    "message": "Starting checkout",
    "host": "Rama",
    "user": "Ramazan",
    "pid": 14456,
    "thread": 16576,
    "label": 0
  },
  {
    "run_id": 1465,
    "timestamp": "2025-05-22T07:31:57.716404",
    "stage": "checkout",
    "status": "INFO",
    "message": "Fetching remote refs",
    "host": "Rama",
    "user": "Ramazan",
    "pid": 14456,
    "thread": 16576,
    "label": 0
  },
  {
    "run_id": 1465,
    "timestamp": "2025-05-22T07:32:19.602986",
    "stage": "checkout",
    "status": "INFO",
    "message": "Repository checked out successfully",
    "host": "Rama",
    "user": "Ramazan",
    "pid": 14456,
    "thread": 16576,
    "duration_sec": 21.886582,
    "label": 0
  },
  {
    "run_id": 1465,
    "timestamp": "2025-05-22T07:32:21.052625",
    "stage": "install",
    "status": "INFO",
    "message": "Starting install",
    "host": "Rama",
    "user": "Ramazan",
    "pid": 14456,
    "thread": 16576,
    "label": 0
  },
  {
    "run_id": 1465,
    "timestamp": "2025-05-22T07:32:28.383380",
    "stage": "install",
    "status": "INFO",
    "message": "Resolving dependencies",
    "host": "Rama",
    "user": "Ramazan",
    "pid": 14456,
    "thread": 16576,
    "label": 0
  },
  {
    "run_id": 1465,
    "timestamp": "2025-05-22T07:32:32.899680",
    "stage": "install",
    "status": "INFO",
    "message": "Downloading packages",
    "host": "Rama",
    "user": "Ramazan",
    "pid": 14456,
    "thread": 16576,
    "label": 0
  },
  {
    "run_id": 1465,
    "timestamp": "2025-05-22T07:32:50.491621",
    "stage": "install",
    "status": "INFO",
    "message": "All packages installed",
    "host": "Rama",
    "user": "Ramazan",
    "pid": 14456,
    "thread": 16576,
    "duration_sec": 17.591941,
    "label": 0
  },
  {
    "run_id": 1465,
    "timestamp": "2025-05-22T07:32:53.381425",
    "stage": "build",
    "status": "INFO",
    "message": "Starting build",
    "host": "Rama",
    "user": "Ramazan",
    "pid": 14456,
    "thread": 16576,
    "label": 0
  },
  {
    "run_id": 1465,
    "timestamp": "2025-05-22T07:33:04.569034",
    "stage": "build",
    "status": "INFO",
    "message": "Build completed in 11.19s",
    "host": "Rama",
    "user": "Ramazan",
    "pid": 14456,
    "thread": 16576,
    "duration_sec": 11.187609,
    "label": 0
  },
  {
    "run_id": 1465,
    "timestamp": "2025-05-22T07:33:06.668377",
    "stage": "test",
    "status": "INFO",
    "message": "Starting test",
    "host": "Rama",
    "user": "Ramazan",
    "pid": 14456,
    "thread": 16576,
    "label": 0
  },
  {
    "run_id": 1465,
    "timestamp": "2025-05-22T07:33:12.589475",
    "stage": "test",
    "status": "INFO",
    "message": "Collecting test results",
    "host": "Rama",
    "user": "Ramazan",
    "pid": 14456,
    "thread": 16576,
    "label": 0
  },
  {
    "run_id": 1465,
    "timestamp": "2025-05-22T07:33:42.566297",
    "stage": "test",
    "status": "INFO",
    "message": "All tests passed",
    "host": "Rama",
    "user": "Ramazan",
    "pid": 14456,
    "thread": 16576,
    "duration_sec": 29.976822,
    "label": 0
  },
  {
    "run_id": 1465,
    "timestamp": "2025-05-22T07:33:44.571061",
    "stage": "deploy",
    "status": "INFO",
    "message": "Starting deploy",
    "host": "Rama",
    "user": "Ramazan",
    "pid": 14456,
    "thread": 16576,
    "label": 0
  },
  {
    "run_id": 1465,
    "timestamp": "2025-05-22T07:33:57.213278",
    "stage": "deploy",
    "status": "INFO",
    "message": "Verifying health checks",
    "host": "Rama",
    "user": "Ramazan",
    "pid": 14456,
    "thread": 16576,
    "label": 0
  },
  {
    "run_id": 1465,
    "timestamp": "2025-05-22T07:34:11.963081",
    "stage": "deploy",
    "status": "INFO",
    "message": "Deployment succeeded",
    "host": "Rama",
    "user": "Ramazan",
    "pid": 14456,
    "thread": 16576,
    "duration_sec": 14.749803,
    "label": 0
  }
]